env_repair/__init__.py
env_repair/__main__.py
env_repair/cli.py
env_repair/clobber.py
env_repair/conda_config.py
env_repair/conda_ops.py
env_repair/conflicts.py
env_repair/discovery.py
env_repair/doctor.py
env_repair/i18n.py
env_repair/inconsistent.py
env_repair/naming.py
env_repair/pip_ops.py
env_repair/progress.py
env_repair/repair.py
env_repair/scan.py
env_repair/search_parse.py
env_repair/subprocess_utils.py
env_repair/verify_imports.py
env_repair-0.2.3.dist-info/licenses/LICENSE
env_repair-0.2.3.dist-info/METADATA
env_repair-0.2.3.dist-info/WHEEL
env_repair-0.2.3.dist-info/entry_points.txt
env_repair-0.2.3.dist-info/top_level.txt
env_repair-0.2.3.dist-info/RECORD
