Metadata-Version: 2.4
Name: env-repair
Version: 0.2.3
Summary: Scan and repair conda/mamba/micromamba environments with mixed conda/pip installs.
Author: Tobias
License-Expression: MIT
Keywords: conda,mamba,micromamba,pip,env,doctor
Classifier: Programming Language :: Python :: 3
Classifier: Programming Language :: Python :: 3 :: Only
Requires-Python: >=3.9
License-File: LICENSE
Provides-Extra: dev
Requires-Dist: pytest>=7; extra == "dev"
Requires-Dist: build>=1.0; extra == "dev"
Dynamic: license-file
